[
  {
    "id": "lipograma-a",
    "title": "Lipograma en A",
    "category": "Juegos lingüísticos",
    "date": "2025-05-15T10:00:00Z"
  },
  {
    "id": "lipograma-e",
    "title": "Lipograma en E",
    "category": "Juegos lingüísticos",
    "date": "2025-05-16T10:00:00Z"
  },
  {
    "id": "lipograma-i",
    "title": "Lipograma en I",
    "category": "Juegos lingüísticos",
    "date": "2025-05-20T10:00:00Z"
  },
  {
    "id": "lipograma-o",
    "title": "Lipograma en O",
    "category": "Juegos lingüísticos",
    "date": "2025-04-15T10:00:00Z"
  },
  {
    "id": "lipograma-u",
    "title": "Lipograma en U",
    "category": "Juegos lingüísticos",
    "date": "2025-04-28T10:00:00Z"
  },
  {
    "id": "solo-sintg-nom",
    "title": "Solo sintagmas nominales",
    "category": "Juegos lingüísticos",
    "date": "2025-04-15T10:00:00Z"
  },
  {
    "id": "onomato",
    "title": "Onomatopeyas",
    "category": "Juegos lingüísticos",
    "date": "2025-04-15T10:00:00Z"
  },
  {
    "id": "silaba-encadenada",
    "title": "Sílaba encadenada",
    "category": "Juegos lingüísticos",
    "date": "2025-04-15T10:00:00Z"
  },
  {
    "id": "infinitivos",
    "title": "Solo infinitivos",
    "category": "Juegos lingüísticos",
    "date": "2025-04-15T10:00:00Z"
  },
  {
    "id": "soneto",
    "title": "Soneto",
    "category": "Formato",
    "subcategory": "Poesía",
    "date": "2025-04-25T10:00:00Z"
  },
  {
    "id": "mester-clerecia",
    "title": "Mester de Clerecía",
    "category": "Formato",
    "subcategory": "Poesía",
    "date": "2025-06-19T10:00:00Z"
  },
  {
    "id": "mester-juglaria",
    "title": "Mester de Juglaría",
    "category": "Formato",
    "subcategory": "Poesía",
    "date": "2025-06-18T10:00:00Z"
  },
  {
    "id": "rebobinado",
    "title": "Rebobinado",
    "category": "Formato",
     "subcategory": "Estructura Narrativa",
    "date": "2025-04-15T10:00:00Z"
  },
  {
    "id": "descompuesto",
    "title": "Descompuesto",
    "category": "Personaje-Narrador",
    "date": "2025-04-15T10:00:00Z"
  },
  {
    "id": "impreciso",
    "title": "Impreciso",
    "category": "Personaje-Narrador",
    "date": "2025-06-15T10:00:00Z"
  },
  {
    "id": "manifiesto",
    "title": "Manifiesto del higo rÚstico",
    "category": "Personaje-Narrador",
    "date": "2025-04-15T10:00:00Z"
  },
  {
    "id": "numerofilo",
    "title": "Numerófilo",
    "category": "Personaje-Narrador",
    "date": "2025-04-15T10:00:00Z"
  },
  {
    "id": "pasivo-agresivo",
    "title": "Pasivo-agresivo",
    "category": "Personaje-Narrador",
    "date": "2025-06-14T10:00:00Z"
  },
   {
    "id": "perfeccionista",
    "title": "Perfeccionista",
    "category": "Personaje-Narrador",
    "date": "2025-06-16T10:00:00Z",
     "requires_script": true
  },
  {
    "id": "transicionario",
    "title": "Transicionario",
    "category": "Personaje-Narrador",
    "date": "2025-06-15T10:00:00Z"
  },
  {
    "id": "trendy",
    "title": "Trendy",
    "category": "Personaje-Narrador",
    "date": "2025-05-15T10:00:00Z"
  },
  {
    "id": "wasap-sim",
    "title": "Whatsapp Simón",
    "category": "Personaje-Narrador",
    "date": "2025-04-24T10:00:00Z"
  },
   {
    "id": "escape-room",
    "title": "Escape Room",
    "category": "Formato",
      "subcategory": "Interactivo",
    "date": "2025-04-15T10:00:00Z"
  },
  {
    "id": "propia-aventura",
    "title": "Elige tu propia aventura",
    "category": "Formato",
      "subcategory": "Interactivo",
    "date": "2025-04-15T10:00:00Z"
  } 
]
